LICENCE.txt
MANIFEST.in
README.rst
setup.py
sveeaccounts/__init__.py
sveeaccounts/backends.py
sveeaccounts/crispies.py
sveeaccounts/crumbs.py
sveeaccounts/forms.py
sveeaccounts/models.py
sveeaccounts/urls.py
sveeaccounts/views.py
sveeaccounts.egg-info/PKG-INFO
sveeaccounts.egg-info/SOURCES.txt
sveeaccounts.egg-info/dependency_links.txt
sveeaccounts.egg-info/not-zip-safe
sveeaccounts.egg-info/requires.txt
sveeaccounts.egg-info/top_level.txt
sveeaccounts/templates/registration/activate.html
sveeaccounts/templates/registration/activation_complete.html
sveeaccounts/templates/registration/activation_email.txt
sveeaccounts/templates/registration/activation_email_subject.txt
sveeaccounts/templates/registration/base.html
sveeaccounts/templates/registration/blocked.html
sveeaccounts/templates/registration/login.html
sveeaccounts/templates/registration/menu.html
sveeaccounts/templates/registration/password_reset_complete.html
sveeaccounts/templates/registration/password_reset_confirm.html
sveeaccounts/templates/registration/password_reset_done.html
sveeaccounts/templates/registration/password_reset_email.html
sveeaccounts/templates/registration/password_reset_form.html
sveeaccounts/templates/registration/registration_closed.html
sveeaccounts/templates/registration/registration_complete.html
sveeaccounts/templates/registration/registration_form.html
sveeaccounts/templates/registration/user_form.html