Metadata-Version: 1.0
Name: sveeaccounts
Version: 0.4
Summary: 
